{"msg":"", "data":[{"id":2,"region_id":1,"name":"Auckland","hasc":"AL","region_name":"Auckland"},{"id":30,"region_id":1,"name":"Manukau","hasc":"MK","region_name":"Auckland"},{"id":37,"region_id":1,"name":"North Shore","hasc":"NS","region_name":"Auckland"},{"id":41,"region_id":1,"name":"Papakura","hasc":"PP","region_name":"Auckland"},{"id":45,"region_id":1,"name":"Rodney","hasc":"RD","region_name":"Auckland"},{"id":66,"region_id":1,"name":"Waitakere","hasc":"WA","region_name":"Auckland"},{"id":26,"region_id":2,"name":"Kawerau","hasc":"KW","region_name":"Bay of Plenty"},{"id":38,"region_id":2,"name":"Opotiki","hasc":"OP","region_name":"Bay of Plenty"},{"id":57,"region_id":2,"name":"Tauranga","hasc":"TG","region_name":"Bay of Plenty"},{"id":71,"region_id":2,"name":"Western Bay of Plenty","hasc":"WB","region_name":"Bay of Plenty"},{"id":73,"region_id":2,"name":"Whakatane","hasc":"WH","region_name":"Bay of Plenty"},{"id":1,"region_id":3,"name":"Ashburton","hasc":"AB","region_name":"Canterbury"},{"id":3,"region_id":3,"name":"Banks Peninsula","hasc":"BK","region_name":"Canterbury"},{"id":9,"region_id":3,"name":"Christchurch","hasc":"CC","region_name":"Canterbury"},{"id":21,"region_id":3,"name":"Hurunui","hasc":"HN","region_name":"Canterbury"},{"id":23,"region_id":3,"name":"Kaikoura","hasc":"KK","region_name":"Canterbury"},{"id":28,"region_id":3,"name":"Mackenzie","hasc":"MZ","region_name":"Canterbury"},{"id":48,"region_id":3,"name":"Selwyn","hasc":"SY","region_name":"Canterbury"},{"id":59,"region_id":3,"name":"Timaru","hasc":"TU","region_name":"Canterbury"},{"id":62,"region_id":3,"name":"Waimakariri","hasc":"WR","region_name":"Canterbury"},{"id":63,"region_id":3,"name":"Waimate","hasc":"WM","region_name":"Canterbury"},{"id":8,"region_id":4,"name":"Chatham Islands","hasc":"CT","region_name":"Chatham Islands"},{"id":14,"region_id":5,"name":"Gisborne","hasc":"GB","region_name":"Gisborne"},{"id":6,"region_id":6,"name":"Central Hawke's Bay","hasc":"CH","region_name":"Hawke's Bay"},{"id":18,"region_id":6,"name":"Hastings","hasc":"HS","region_name":"Hawke's Bay"},{"id":34,"region_id":6,"name":"Napier","hasc":"NR","region_name":"Hawke's Bay"},{"id":65,"region_id":6,"name":"Wairoa","hasc":"WW","region_name":"Hawke's Bay"},{"id":20,"region_id":7,"name":"Horowhenua","hasc":"HW","region_name":"Manawatu-Wanganui"},{"id":29,"region_id":7,"name":"Manawatu","hasc":"MN","region_name":"Manawatu-Wanganui"},{"id":40,"region_id":7,"name":"Palmerston North","hasc":"PN","region_name":"Manawatu-Wanganui"},{"id":44,"region_id":7,"name":"Rangitikei","hasc":"RT","region_name":"Manawatu-Wanganui"},{"id":47,"region_id":7,"name":"Ruapehu","hasc":"RP","region_name":"Manawatu-Wanganui"},{"id":54,"region_id":7,"name":"Tararua","hasc":"TR","region_name":"Manawatu-Wanganui"},{"id":69,"region_id":7,"name":"Wanganui","hasc":"WU","region_name":"Manawatu-Wanganui"},{"id":31,"region_id":8,"name":"Marlborough","hasc":"MB","region_name":"Marlborough"},{"id":35,"region_id":9,"name":"Nelson","hasc":"NL","region_name":"Nelson"},{"id":12,"region_id":10,"name":"Far North","hasc":"FN","region_name":"Northland"},{"id":24,"region_id":10,"name":"Kaipara","hasc":"KP","region_name":"Northland"},{"id":74,"region_id":10,"name":"Whangarei","hasc":"WN","region_name":"Northland"},{"id":7,"region_id":11,"name":"Central Otago","hasc":"CO","region_name":"Otago"},{"id":10,"region_id":11,"name":"Clutha","hasc":"CL","region_name":"Otago"},{"id":11,"region_id":11,"name":"Dunedin","hasc":"DU","region_name":"Otago"},{"id":43,"region_id":11,"name":"Queenstown-Lakes","hasc":"QL","region_name":"Otago"},{"id":67,"region_id":11,"name":"Waitaki","hasc":"WI","region_name":"Otago"},{"id":15,"region_id":12,"name":"Gore","hasc":"GO","region_name":"Southland"},{"id":22,"region_id":12,"name":"Invercargill","hasc":"IC","region_name":"Southland"},{"id":49,"region_id":12,"name":"Southland","hasc":"SL","region_name":"Southland"},{"id":36,"region_id":13,"name":"New Plymouth","hasc":"NP","region_name":"Taranaki"},{"id":50,"region_id":13,"name":"South Taranaki","hasc":"ST","region_name":"Taranaki"},{"id":53,"region_id":13,"name":"Stratford","hasc":"SF","region_name":"Taranaki"},{"id":55,"region_id":14,"name":"Tasman","hasc":"TM","region_name":"Tasman"},{"id":13,"region_id":15,"name":"Franklin","hasc":"FK","region_name":"Waikato"},{"id":17,"region_id":15,"name":"Hamilton","hasc":"HM","region_name":"Waikato"},{"id":19,"region_id":15,"name":"Hauraki","hasc":"HK","region_name":"Waikato"},{"id":33,"region_id":15,"name":"Matamata-Piako","hasc":"MP","region_name":"Waikato"},{"id":39,"region_id":15,"name":"Otorohanga","hasc":"OH","region_name":"Waikato"},{"id":46,"region_id":15,"name":"Rotorua","hasc":"RR","region_name":"Waikato"},{"id":51,"region_id":15,"name":"South Waikato","hasc":"SW","region_name":"Waikato"},{"id":56,"region_id":15,"name":"Taupo","hasc":"TP","region_name":"Waikato"},{"id":58,"region_id":15,"name":"Thames-Coromandel","hasc":"TC","region_name":"Waikato"},{"id":61,"region_id":15,"name":"Waikato","hasc":"WT","region_name":"Waikato"},{"id":64,"region_id":15,"name":"Waipa","hasc":"WP","region_name":"Waikato"},{"id":68,"region_id":15,"name":"Waitomo","hasc":"WO","region_name":"Waikato"},{"id":5,"region_id":16,"name":"Carterton","hasc":"CR","region_name":"Wellington"},{"id":25,"region_id":16,"name":"Kapiti Coast","hasc":"KC","region_name":"Wellington"},{"id":27,"region_id":16,"name":"Lower Hutt","hasc":"LH","region_name":"Wellington"},{"id":32,"region_id":16,"name":"Masterton","hasc":"MT","region_name":"Wellington"},{"id":42,"region_id":16,"name":"Porirua","hasc":"PR","region_name":"Wellington"},{"id":52,"region_id":16,"name":"South Wairarapa","hasc":"SP","region_name":"Wellington"},{"id":60,"region_id":16,"name":"Upper Hutt","hasc":"UH","region_name":"Wellington"},{"id":70,"region_id":16,"name":"Wellington","hasc":"WE","region_name":"Wellington"},{"id":4,"region_id":17,"name":"Buller","hasc":"BU","region_name":"West Coast"},{"id":16,"region_id":17,"name":"Grey","hasc":"GR","region_name":"West Coast"},{"id":72,"region_id":17,"name":"Westland","hasc":"WL","region_name":"West Coast"}]}