{"Columns":[{"ShortTypeName":"OrderDetail","strDateType":"orderdetail","DataType":4,"Name":"OrderDetails","DisplayName":"订单明细","Nullable":true,"MaxLength":0,"RangeMin":0,"RangeMax":0,"IsVisible":true,"IsNumeric":false,"HasMetaAttribute":false,"MetaAttribute":""},{"ShortTypeName":"int","strDateType":"int","DataType":1,"Name":"Id","DisplayName":"Id","Nullable":true,"MaxLength":0,"RangeMin":0,"RangeMax":0,"IsVisible":true,"IsNumeric":true,"HasMetaAttribute":false,"MetaAttribute":""},{"ShortTypeName":"string","strDateType":"string","DataType":0,"Name":"Customer","DisplayName":"客户","Nullable":true,"MaxLength":50,"RangeMin":0,"RangeMax":0,"IsVisible":true,"IsNumeric":false,"HasMetaAttribute":true,"MetaAttribute":"[MaxLength(50)]"},{"ShortTypeName":"string","strDateType":"string","DataType":0,"Name":"ShippingAddress","DisplayName":"发货地址","Nullable":true,"MaxLength":255,"RangeMin":0,"RangeMax":0,"IsVisible":true,"IsNumeric":false,"HasMetaAttribute":true,"MetaAttribute":"[MaxLength(255)]"},{"ShortTypeName":"DateTime","strDateType":"datetime","DataType":2,"Name":"OrderDate","DisplayName":"订单日期","Nullable":true,"MaxLength":0,"RangeMin":0,"RangeMax":0,"IsVisible":true,"IsNumeric":false,"HasMetaAttribute":false,"MetaAttribute":""}]}